README.md
setup.py
scrapy_demo/__init__.py
scrapy_demo.egg-info/PKG-INFO
scrapy_demo.egg-info/SOURCES.txt
scrapy_demo.egg-info/dependency_links.txt
scrapy_demo.egg-info/requires.txt
scrapy_demo.egg-info/top_level.txt
scrapy_demo/scrapy_demo/__init__.py
scrapy_demo/scrapy_demo/items.py
scrapy_demo/scrapy_demo/middlewares.py
scrapy_demo/scrapy_demo/pipelines.py
scrapy_demo/scrapy_demo/run_spider.py
scrapy_demo/scrapy_demo/settings.py
scrapy_demo/scrapy_demo/spiders/__init__.py
scrapy_demo/scrapy_demo/spiders/test.py